LICENSE
MANIFEST.in
README-pypi.rst
README.rst
pyproject.toml
test_openapi.py
test_rest.py
test_schema.py
inema/__init__.py
inema/data.py
inema/frank.py
inema/inema.py
inema/rest.py
inema/soapfree.py
inema/utils.py
inema/wpint.py
inema.egg-info/PKG-INFO
inema.egg-info/SOURCES.txt
inema.egg-info/dependency_links.txt
inema.egg-info/entry_points.txt
inema.egg-info/requires.txt
inema.egg-info/top_level.txt
inema/data/formats.json
inema/data/products.json