Metadata-Version: 2.4
Name: inema
Version: 1.0.2
Summary: A Python interface to the Deutsche Post Internetmarke and Warenpost International Online Franking
Author-email: Georg Sauthoff <mail@gms.tf>, Harald Welte <hwelte@sysmocom.de>
License-Expression: LGPL-3.0-or-later
Project-URL: Homepage, https://git.sysmocom.de/odoo/python-inema/
Project-URL: Documentation, https://inema.readthedocs.io/
Project-URL: Issues, https://codeberg.org/gms/python-inema/issues
Classifier: Development Status :: 5 - Production/Stable
Classifier: Operating System :: OS Independent
Classifier: Programming Language :: Python :: 3
Classifier: Topic :: Office/Business
Requires-Python: >=3.8
License-File: LICENSE
Requires-Dist: requests
Requires-Dist: lxml
Requires-Dist: pytz
Requires-Dist: zeep>=0.12.0
Provides-Extra: dev
Requires-Dist: pytest; extra == "dev"
Requires-Dist: jsonref; extra == "dev"
Requires-Dist: jsonschema; extra == "dev"
Requires-Dist: openapi-core; extra == "dev"
Requires-Dist: responses; extra == "dev"
Dynamic: license-file
